pysonlib/__init__.py
pysonlib/__main__.py
pysonlib/pyson_helper.py
pysonlib/pyson_object.py
pysonlib/resources.py
tests/__init__.py
tests/test_one.py
pysonlib-0.0.2.dist-info/LICENSE
pysonlib-0.0.2.dist-info/METADATA
pysonlib-0.0.2.dist-info/WHEEL
pysonlib-0.0.2.dist-info/top_level.txt
pysonlib-0.0.2.dist-info/RECORD
